morphopy/MorphoPy.py
morphopy/__init__.py
morphopy/about/__init__.py
morphopy/computation/__init__.py
morphopy/computation/feature_presentation.py
morphopy/computation/file_manager.py
morphopy/computation/persistence_functions.py
morphopy/neurontree/NeuronTree.py
morphopy/neurontree/__init__.py
morphopy/neurontree/plotting.py
morphopy/neurontree/utils.py
morphopy-0.7.5.dist-info/METADATA
morphopy-0.7.5.dist-info/WHEEL
morphopy-0.7.5.dist-info/licenses/LICENSE
morphopy-0.7.5.dist-info/RECORD
