Metadata-Version: 2.4
Name: morphopy
Version: 0.7.5
Summary: A Python package for feature extraction of neural morphologies
License-Expression: MIT
License-File: LICENSE
Requires-Python: >=3.10
Requires-Dist: matplotlib
Requires-Dist: matplotlib-scalebar
Requires-Dist: networkx
Requires-Dist: numpy
Requires-Dist: pandas
Requires-Dist: plotly
Requires-Dist: pytest>=8.3.5
Requires-Dist: scikit-learn
Requires-Dist: scipy
Requires-Dist: seaborn
Requires-Dist: shapely
